pyprodrisk/__init__.py
pyprodrisk/prodrisk_runner.py
pyprodrisk/helpers/__init__.py
pyprodrisk/helpers/commands.py
pyprodrisk/helpers/time.py
pyprodrisk/helpers/timeseries.py
pyprodrisk/helpers/topoplot.py
pyprodrisk/prodrisk_core/__init__.py
pyprodrisk/prodrisk_core/command_builder.py
pyprodrisk/prodrisk_core/model_builder.py
pyprodrisk/prodrisk_core/prodrisk_api.py
pyprodrisk-2.0.2.dist-info/licenses/LICENSE
pyprodrisk-2.0.2.dist-info/METADATA
pyprodrisk-2.0.2.dist-info/WHEEL
pyprodrisk-2.0.2.dist-info/top_level.txt
pyprodrisk-2.0.2.dist-info/RECORD
