Metadata-Version: 2.4
Name: pyprodrisk
Version: 2.0.2
Summary: Python interface to Prodrisk
Home-page: https://www.sintef.no/en/software/prodrisk
Author: SINTEF Energy Research
Author-email: support.energy@sintef.no
License: MIT
Project-URL: README, https://gitlab.sintef.no/energy/prodrisk/pyprodrisk/-/blob/main/README.md
Project-URL: Documentation, https://docs.prodrisk.sintef.energy/examples/interacting_prodrisk/pyprodrisk_basic/pyprodrisk_basic.html
Project-URL: Source, https://gitlab.sintef.no/energy/prodrisk/pyprodrisk
Project-URL: Tracker, https://prodrisk.sintef.energy/tickets
Classifier: Development Status :: 5 - Production/Stable
Classifier: License :: OSI Approved :: MIT License
Classifier: Intended Audience :: Developers
Classifier: Intended Audience :: End Users/Desktop
Classifier: Intended Audience :: Education
Classifier: Intended Audience :: Science/Research
Classifier: Topic :: Scientific/Engineering
Classifier: Programming Language :: Python :: 3.10
Classifier: Programming Language :: Python :: 3.11
Classifier: Programming Language :: Python :: 3.12
Classifier: Programming Language :: Python :: 3.13
Classifier: Operating System :: POSIX :: Linux
Classifier: Operating System :: Microsoft :: Windows
Requires-Python: >=3.10
License-File: LICENSE
Requires-Dist: pandas
Requires-Dist: numpy
Requires-Dist: graphviz
Requires-Dist: pybind11
Provides-Extra: full
Requires-Dist: pyyaml; extra == "full"
Requires-Dist: tables; extra == "full"
Requires-Dist: scipy; extra == "full"
Requires-Dist: matplotlib; extra == "full"
Dynamic: author
Dynamic: author-email
Dynamic: classifier
Dynamic: description
Dynamic: description-content-type
Dynamic: home-page
Dynamic: license
Dynamic: license-file
Dynamic: project-url
Dynamic: provides-extra
Dynamic: requires-dist
Dynamic: requires-python
Dynamic: summary
